EUBTA/__init__.py
mi_libreria-4.0.dist-info/LICENSE
mi_libreria-4.0.dist-info/METADATA
mi_libreria-4.0.dist-info/WHEEL
mi_libreria-4.0.dist-info/top_level.txt
mi_libreria-4.0.dist-info/RECORD
