Metadata-Version: 2.1
Name: mi-libreria
Version: 4.0
Summary: Hard encode algorithm
Home-page: https://github.com/Lucas-Varela-Correa/Encode-Using-Binary-Tree
Author: Lucas Varela Correa
Author-email: lucasvarelacorrea@gmail.com
License: UNKNOWN
Platform: UNKNOWN
Classifier: Programming Language :: Python :: 3
Classifier: License :: OSI Approved :: MIT License
Classifier: Operating System :: OS Independent
Requires-Python: >=3.6
License-File: LICENSE
